automojo/errors/__init__.py
automojo/errors/exceptions.py
automojo/errors/raising.py
automojo/errors/xtraceback.py
automojo_errors-0.0.1.dist-info/LICENSE.txt
automojo_errors-0.0.1.dist-info/METADATA
automojo_errors-0.0.1.dist-info/WHEEL
automojo_errors-0.0.1.dist-info/RECORD
