Metadata-Version: 2.1
Name: automojo-errors
Version: 0.0.1
Summary: Automation Mojo - Errors
License: LICENSE.txt
Keywords: python
Requires-Python: >=3.10,<4.0
Classifier: License :: OSI Approved :: MIT License
Classifier: License :: Other/Proprietary License
Classifier: Operating System :: POSIX
Classifier: Programming Language :: Python :: 3
Classifier: Programming Language :: Python :: 3.10
Classifier: Programming Language :: Python :: 3.11
Classifier: Programming Language :: Python :: 3.12
